ruamel.std.typing-0.1.2-py3.8-nspkg.pth
ruamel/std/typing/__init__.py
ruamel.std.typing-0.1.2.dist-info/LICENSE
ruamel.std.typing-0.1.2.dist-info/METADATA
ruamel.std.typing-0.1.2.dist-info/WHEEL
ruamel.std.typing-0.1.2.dist-info/namespace_packages.txt
ruamel.std.typing-0.1.2.dist-info/top_level.txt
ruamel.std.typing-0.1.2.dist-info/RECORD
