Metadata-Version: 2.1
Name: ruamel.std.typing
Version: 0.1.2
Summary: wrapper to handle dependency differences between version, and missing Text in 3.5.0/1
Home-page: https://sourceforge.net/p/ruamel-std-typing/code/ci/default/tree
Author: Anthon van der Neut
Author-email: a.van.der.neut@ruamel.eu
License: MIT License
Platform: UNKNOWN
Classifier: Development Status :: 4 - Beta
Classifier: Intended Audience :: Developers
Classifier: License :: OSI Approved :: MIT License
Classifier: Operating System :: OS Independent
Classifier: Programming Language :: Python
Requires-Dist: typing ; python_version < "3.5"
